galmak.py
gallery_maker-0.0.1.dist-info/LICENSE
gallery_maker-0.0.1.dist-info/METADATA
gallery_maker-0.0.1.dist-info/WHEEL
gallery_maker-0.0.1.dist-info/entry_points.txt
gallery_maker-0.0.1.dist-info/top_level.txt
gallery_maker-0.0.1.dist-info/RECORD
