Metadata-Version: 2.1
Name: gallery-maker
Version: 0.0.1
Summary: Make an html file for an image gallery.
Author-email: Vedrana Dahl <vedranaa@gmail.com>
Project-URL: Homepage, https://github.com/vedranaa/gallery_maker
Classifier: Programming Language :: Python :: 3
Classifier: License :: OSI Approved :: MIT License
Classifier: Operating System :: OS Independent
Requires-Python: >=3.8
License-File: LICENSE
